{
  "generator-jhipster": {
    "promptValues": {
      "packageName": "com.mycompany.myapp",
      "nativeLanguage": "pt-br"
    },
    "jhipsterVersion": "5.7.1",
    "applicationType": "monolith",
    "baseName": "myApp",
    "packageName": "com.mycompany.myapp",
    "packageFolder": "com/mycompany/myapp",
    "serverPort": "8080",
    "authenticationType": "jwt",
    "cacheProvider": "ehcache",
    "enableHibernateCache": true,
    "websocket": false,
    "databaseType": "sql",
    "devDatabaseType": "h2Disk",
    "prodDatabaseType": "mysql",
    "searchEngine": false,
    "messageBroker": false,
    "serviceDiscoveryType": false,
    "buildTool": "maven",
    "enableSwaggerCodegen": false,
    "jwtSecretKey": "MzdmOTllYzczOTFjM2UyYmIzMWQ5NjRkNzIyOGY2NjIwOTRlZTkwODEwOTM4ZDYxNzU3ODJlOGE2ODMzMmU3MjhmNTJkMjg5ZjVkYTI5ZGNkMjE0MTM5N2RkY2RkOGQ5ZWQ3MDg3MjYyNGNkODVhNzVmZDQ3MDg3ZGZlMzE4MGE=",
    "clientFramework": "angularX",
    "useSass": false,
    "clientPackageManager": "npm",
    "testFrameworks": [],
    "jhiPrefix": "jhi",
    "otherModules": [],
    "enableTranslation": true,
    "nativeLanguage": "pt-br",
    "languages": [
      "pt-br"
    ]
  }
}